Workbook

Sheet Welcome
A1: Opus Pulse - TNM to Outcome Conversion Simulator
A2: A live model. Change any YELLOW input and every result, table and chart recalculates instantly.
A4: How to use
B5: Yellow cells | C5: are the only inputs you edit - team, rates, calendar, expenses, capacity, efficiency and discount.
B6: Everything else | C6: is a live, IFERROR-guarded formula - no #DIV/0! or #N/A, even mid-edit.
B7: Charts | C7: read from the formula cells, so they redraw automatically.
A8: The tabs
B9: Rate Card | C9: Standard billing rate per role and experience. Billing looks rates up from here.
B10: Billing (TNM) | C10: Time & Material: team + calendar + expenses -> monthly & yearly billing, profit and margin.
B11: Outcome | C11: Outcome conversion: two capacity cases, price per story point, and the client win-win.
B12: Dashboard | C12: One-screen verdict: TNM vs Outcome and who benefits.
A13: Key formulas
B14: Billable days/yr | C14: 365 - 104 weekends - holidays - leaves
B15: Monthly billing | C15: sum of (count x rate) x billable hours per month
B16: Break-even price/SP | C16: TNM monthly billing / deliverable SP per month
B17: Recommended price/SP | C17: break-even x (1 - client discount %)
B18: Outcome cost/month | C18: TNM monthly cost / (1 + efficiency gain %)
B19: Win-win test | C19: client pays less than TNM AND Opus profit is not lower
B21: Legend: | C21: yellow = input | white/blue = formula (do not edit)

Sheet Rate Card
A1: Account Rate Card - Apex Bank
A2: Standard billing rate by role and experience. YELLOW = editable.
A4: Role | B4: Experience (yrs) | C4: Billing Rate/hr
A5: Sr Dev | B5: 5 to 8 | C5: 28 | F5: =A5&"|"&B5
A6: Sr Dev | B6: 8 to 10 | C6: 30 | F6: =A6&"|"&B6
A7: Tech Lead (Dev) | B7: 9 to 12 | C7: 35 | F7: =A7&"|"&B7
A8: Sr QA | B8: 5 to 8 | C8: 28 | F8: =A8&"|"&B8
A9: Lead QA | B9: 9 to 12 | C9: 35 | F9: =A9&"|"&B9
A10: PO | B10: 12 to 14 | C10: 37 | F10: =A10&"|"&B10
A11: Developer | B11: 3 to 5 | C11: 22 | F11: =A11&"|"&B11
A12: QA Engineer | B12: 3 to 5 | C12: 20 | F12: =A12&"|"&B12
A13: Architect | B13: 12 to 14 | C13: 45 | F13: =A13&"|"&B13
A14: Business Analyst | B14: 5 to 8 | C14: 30 | F14: =A14&"|"&B14

Sheet Billing (TNM)
A1: Billing Simulator - Time & Material (TNM)
A2: YELLOW = inputs. Revenue, profit and margin are live formulas.
A4: Company calendar & hours | H4: Monthly | I4: $
A5: Hours per day | B5: 8 | H5: Revenue | I5: =B34
A6: Weekend days / year | B6: 104 | H6: Expenses | I6: =B36
A7: Public holidays / year | B7: 10 | H7: Profit | I7: =B38
A8: Leaves / year | B8: 21
A9: Billable days / year | B9: =365-B6-B7-B8
A10: Billable hours / year (per resource) | B10: =B9*B5
A11: Billable hours / month (per resource) | B11: =B10/12
A13: Project team (pick role & experience - rate auto-fills from the Rate Card)
A14: Role | B14: Experience | C14: Count | D14: Rate/hr | E14: Monthly Revenue | F14: Yearly Revenue
A15: Sr Dev | B15: 5 to 8 | C15: 3 | D15: =IFERROR(INDEX('Rate Card'!$C$5:$C$14,MATCH(A15&"|"&B15,'Rate Card'!$F$5:$F$14,0)),0) | E15: =C15*D15*$B$11 | F15: =C15*D15*$B$10
A16: Sr Dev | B16: 8 to 10 | C16: 2 | D16: =IFERROR(INDEX('Rate Card'!$C$5:$C$14,MATCH(A16&"|"&B16,'Rate Card'!$F$5:$F$14,0)),0) | E16: =C16*D16*$B$11 | F16: =C16*D16*$B$10
A17: Tech Lead (Dev) | B17: 9 to 12 | C17: 1 | D17: =IFERROR(INDEX('Rate Card'!$C$5:$C$14,MATCH(A17&"|"&B17,'Rate Card'!$F$5:$F$14,0)),0) | E17: =C17*D17*$B$11 | F17: =C17*D17*$B$10
A18: Sr QA | B18: 5 to 8 | C18: 1 | D18: =IFERROR(INDEX('Rate Card'!$C$5:$C$14,MATCH(A18&"|"&B18,'Rate Card'!$F$5:$F$14,0)),0) | E18: =C18*D18*$B$11 | F18: =C18*D18*$B$10
A19: Lead QA | B19: 9 to 12 | C19: 2 | D19: =IFERROR(INDEX('Rate Card'!$C$5:$C$14,MATCH(A19&"|"&B19,'Rate Card'!$F$5:$F$14,0)),0) | E19: =C19*D19*$B$11 | F19: =C19*D19*$B$10
A20: PO | B20: 12 to 14 | C20: 1 | D20: =IFERROR(INDEX('Rate Card'!$C$5:$C$14,MATCH(A20&"|"&B20,'Rate Card'!$F$5:$F$14,0)),0) | E20: =C20*D20*$B$11 | F20: =C20*D20*$B$10
A21: Total team | C21: =SUM(C15:C20) | E21: =SUM(E15:E20) | F21: =SUM(F15:F20)
A23: Project expenses (cost)
A24: Category | B24: Amount | C24: Frequency | D24: Yearly Amount
A25: Salaries | B25: 24000 | C25: monthly | D25: =IF(C25="monthly",B25*12,B25)
A26: Infrastructure / seats | B26: 2500 | C26: monthly | D26: =IF(C26="monthly",B26*12,B26)
A27: Software licenses | B27: 1200 | C27: monthly | D27: =IF(C27="monthly",B27*12,B27)
A28: Travel | B28: 700 | C28: monthly | D28: =IF(C28="monthly",B28*12,B28)
A29: Training | B29: 6000 | C29: yearly | D29: =IF(C29="monthly",B29*12,B29)
A30: Total yearly expenses | D30: =SUM(D25:D29)
A31: Total monthly expenses | D31: =D30/12
A33: Results
A34: Monthly billing (revenue) | B34: =E21
A35: Yearly billing (revenue) | B35: =F21
A36: Monthly expenses (cost) | B36: =D31
A37: Yearly expenses (cost) | B37: =D30
A38: Monthly profit | B38: =B34-B36
A39: Yearly profit | B39: =B35-B37
A40: Profit margin % | B40: =IFERROR(B39/B35,0)

Sheet Outcome
A1: Outcome-Based Cost Simulation
A2: Two capacity cases. YELLOW = inputs. Team & cost are inherited from Billing (TNM).
A4: Inputs
A5: Headcount (from Billing) | B5: ='Billing (TNM)'!C21 | N5: Client pays | O5: TNM | P5: Outcome
A6: Per-person SP / sprint - Case 1 | B6: 7 | N6: Case 1 | O6: =$B$13 | P6: =B25
A7: Per-person SP / sprint - Case 2 | B7: 8 | N7: Case 2 | O7: =$B$13 | P7: =C25
A8: Capacity reserve % | B8: 0.15
A9: Sprints per month | B9: 2 | N9: Opus margin | O9: TNM | P9: Outcome
A10: Minimum invoice SP | B10: 120 | N10: Case 1 | O10: =B28 | P10: =B29
A11: Outcome efficiency gain % | B11: 0.1 | N11: Case 2 | O11: =C28 | P11: =C29
A12: Client discount % | B12: 0.05
A13: TNM monthly billing (R) | B13: ='Billing (TNM)'!$B$34 | N13: Price / SP | O13: Break-even | P13: Recommended
A14: Monthly cost (C) | B14: ='Billing (TNM)'!$B$36 | N14: Case 1 | O14: =B23 | P14: =B24
N15: Case 2 | O15: =C23 | P15: =C24
A16: Case 1 vs Case 2
A17: Metric | B17: Case 1 | C17: Case 2
A18: Per-person SP / sprint | B18: =$B$6 | C18: =$B$7
A19: Gross team velocity / sprint | B19: =B18*$B$5 | C19: =C18*$B$5
A20: Effective velocity (after reserve) | B20: =B19*(1-$B$8) | C20: =C19*(1-$B$8)
A21: Deliverable SP / month | B21: =B20*$B$9 | C21: =C20*$B$9
A22: Meets min invoice? | B22: =IF(B21>=$B$10,"Yes","No (short)") | C22: =IF(C21>=$B$10,"Yes","No (short)")
A23: Break-even price / SP | B23: =IFERROR($B$13/B21,0) | C23: =IFERROR($B$13/C21,0)
A24: Recommended price / SP | B24: =B23*(1-$B$12) | C24: =C23*(1-$B$12)
A25: Monthly outcome bill | B25: =B24*B21 | C25: =C24*C21
A26: Yearly outcome bill | B26: =B25*12 | C26: =C25*12
A27: Outcome cost / month | B27: =IFERROR($B$14/(1+$B$11),0) | C27: =IFERROR($B$14/(1+$B$11),0)
A28: Opus margin - TNM | B28: =IFERROR(($B$13-$B$14)/$B$13,0) | C28: =IFERROR(($B$13-$B$14)/$B$13,0)
A29: Opus margin - Outcome | B29: =IFERROR((B25-B27)/B25,0) | C29: =IFERROR((C25-C27)/C25,0)
A30: Margin uplift | B30: =B29-B28 | C30: =C29-C28
A31: Opus profit - TNM / month | B31: =$B$13-$B$14 | C31: =$B$13-$B$14
A32: Opus profit - Outcome / month | B32: =B25-B27 | C32: =C25-C27
A33: Opus extra profit / year | B33: =(B32-B31)*12 | C33: =(C32-C31)*12
A34: Client saving / month | B34: =$B$13-B25 | C34: =$B$13-C25
A35: Client saving / year | B35: =B34*12 | C35: =C34*12
A36: WIN-WIN? | B36: =IF(AND(B25<$B$13,(B25-B27)>=($B$13-$B$14)),"YES - WIN-WIN","Not yet") | C36: =IF(AND(C25<$B$13,(C25-C27)>=($B$13-$B$14)),"YES - WIN-WIN","Not yet")

Sheet Dashboard
A1: Dashboard - TNM vs Outcome (Case 2, feasible)
A2: Headline verdict for the 8 SP/person case.
A4: Headline numbers | D4: Who benefits (annual $)
A5: TNM monthly billing | B5: =Outcome!B13 | D5: Client saving | E5: =Outcome!C35
A6: TNM yearly billing | B6: =Outcome!B13*12 | D6: Opus extra profit | E6: =Outcome!C33
A7: TNM margin | B7: =Outcome!C28
A8: Outcome monthly bill | B8: =Outcome!C25
A9: Outcome margin | B9: =Outcome!C29
A10: Opus extra profit / year | B10: =Outcome!C33
A11: Client saving / year | B11: =Outcome!C35
A13: =Outcome!C36
A16: Both parties end up better off: the client pays less than TNM while Opus earns more - the efficiency Opus keeps under Outcome funds a price the client still finds cheaper.
